gumpy/__init__.py
gumpy/difference.py
gumpy/gene.py
gumpy/genome.py
gumpy/py.typed
gumpy/variantfile.py
gumpy-1.3.8.data/scripts/gumpy-save-genome.py
gumpy-1.3.8.data/scripts/to_piezo_catalogue.py
gumpy-1.3.8.dist-info/LICENSE
gumpy-1.3.8.dist-info/METADATA
gumpy-1.3.8.dist-info/WHEEL
gumpy-1.3.8.dist-info/top_level.txt
gumpy-1.3.8.dist-info/RECORD
