Metadata-Version: 2.1
Name: gumpy
Version: 1.3.8
Summary: Genetics with Numpy
Home-page: https://github.com/oxfordmmm/gumpy
Author: Philip W Fowler
Author-email: philip.fowler@ndm.ox.ac.uk
License: University of Oxford, see LICENSE.md
Classifier: Programming Language :: Python :: 3
Classifier: Operating System :: OS Independent
Requires-Python: >=3.10
License-File: LICENSE
Requires-Dist: numpy
Requires-Dist: pysam
Requires-Dist: biopython
Requires-Dist: tqdm
Requires-Dist: pytest
Requires-Dist: pytest-cov
Requires-Dist: pandas
Requires-Dist: scipy
